lkmlfmt_djhtml/__init__.py
lkmlfmt_djhtml/formatter.py
lkmlfmt_djhtml-0.0.1.dist-info/LICENSE
lkmlfmt_djhtml-0.0.1.dist-info/METADATA
lkmlfmt_djhtml-0.0.1.dist-info/WHEEL
lkmlfmt_djhtml-0.0.1.dist-info/RECORD
