Metadata-Version: 2.1
Name: lkmlfmt-djhtml
Version: 0.0.1
Summary: a plugin for lkmlfmt
Author: kitta65
Author-email: skndr666m1@gmail.com
Requires-Python: >=3.11,<4.0
Classifier: Programming Language :: Python :: 3
Classifier: Programming Language :: Python :: 3.11
Requires-Dist: djhtml (>=3.0.6,<4.0.0)
